{"version":"0.4","title":"landing-numbers","type":"section","content":[{"id":"2901d9bb","settings":{"stretch_section":"section-stretched","background_background":"classic","background_color":"#F8F5FF","padding":{"unit":"px","top":"80","right":"0","bottom":"80","left":"0","isLinked":false}},"elements":[{"id":"fc77583","settings":{"_column_size":100,"_inline_size":null},"elements":[{"id":"4c7e68d8","settings":{"content":"Next-generation applications","max_width":"600px","secondary_font":"secondary-font","size":"h2","_margin":{"unit":"px","top":"0","right":"0","bottom":"-15","left":"0","isLinked":false}},"elements":[],"isInner":false,"widgetType":"pix-sliding-text","elType":"widget"},{"id":"79301ea9","settings":{"content":"Design better and spend less time without restricting creative freedom. Combine layouts, customize everything.","size":"text-20","bold":"","position":"text-center","max_width":"600px","animation":"fade-in-up","delay":"500"},"elements":[],"isInner":false,"widgetType":"pix-text","elType":"widget"},{"id":"741579f3","settings":{"structure":"30"},"elements":[{"id":"2a776247","settings":{"_column_size":33,"_inline_size":null},"elements":[{"id":"748083db","settings":{"media_type":"icon","char":"1","icon":"pixicon-basket-up","animation":"fade-in-up","delay":"0","content_align":"center","icon_color":"primary","icon_size":"48","_margin":{"unit":"px","top":"20","right":"0","bottom":"-20","left":"0","isLinked":false}},"elements":[],"isInner":false,"widgetType":"pix-icon","elType":"widget"},{"id":"69f43f69","settings":{"numbers_style":"numbers-stack","text_before":"+","number":"200","duration":"1000","text_after":"%","content":"Conversion rate increased","title_size":"h1","title_display":"display-3","content_color":"heading-default","content_position":"text-center","_padding":{"unit":"px","top":"0","right":"0","bottom":"10","left":"0","isLinked":false}},"elements":[],"isInner":false,"widgetType":"pix-numbers","elType":"widget"}],"isInner":true,"elType":"column"},{"id":"6616e1f6","settings":{"_column_size":33,"_inline_size":null},"elements":[{"id":"5901caaa","settings":{"media_type":"icon","char":"1","icon":"pixicon-users-2","animation":"fade-in-up","delay":"0","content_align":"center","icon_color":"primary","icon_size":"48","_margin":{"unit":"px","top":"20","right":"0","bottom":"-20","left":"0","isLinked":false}},"elements":[],"isInner":false,"widgetType":"pix-icon","elType":"widget"},{"id":"278a9399","settings":{"numbers_style":"numbers-stack","text_before":"+","number":"16","duration":"1000","text_after":"K","content":"Happy pixfort customers","title_size":"h1","title_display":"display-3","content_color":"heading-default","content_position":"text-center","_padding":{"unit":"px","top":"0","right":"0","bottom":"10","left":"0","isLinked":false}},"elements":[],"isInner":false,"widgetType":"pix-numbers","elType":"widget"}],"isInner":true,"elType":"column"},{"id":"3f2be305","settings":{"_column_size":33,"_inline_size":null},"elements":[{"id":"7de5f040","settings":{"media_type":"icon","char":"1","icon":"pixicon-money2","animation":"fade-in-up","delay":"0","content_align":"center","icon_color":"primary","icon_size":"48","_margin":{"unit":"px","top":"20","right":"0","bottom":"-20","left":"0","isLinked":false}},"elements":[],"isInner":false,"widgetType":"pix-icon","elType":"widget"},{"id":"2adbc689","settings":{"numbers_style":"numbers-stack","text_before":"+","number":"40","duration":"1000","text_after":"M","content":"Amount of investments in 2020","title_size":"h1","title_display":"display-3","content_color":"heading-default","content_position":"text-center","_padding":{"unit":"px","top":"0","right":"0","bottom":"10","left":"0","isLinked":false}},"elements":[],"isInner":false,"widgetType":"pix-numbers","elType":"widget"}],"isInner":true,"elType":"column"}],"isInner":true,"elType":"section"}],"isInner":false,"elType":"column"}],"isInner":false,"elType":"section"}]}
