{"version":"0.4","title":"construction-charts-left","type":"section","content":[{"id":"3c437ede","settings":{"stretch_section":"section-stretched","structure":"20","background_background":"classic","background_color":"#FFFFFF","padding":{"unit":"px","top":"80","right":"0","bottom":"80","left":"0","isLinked":false},"border_border":"solid","border_width":{"unit":"px","top":"1","right":"1","bottom":"1","left":"1","isLinked":true},"border_color":"rgba(0, 0, 0, 0.08)"},"elements":[{"id":"6f39b6eb","settings":{"_column_size":50,"_inline_size":null,"content_position":"center"},"elements":[{"id":"66e28835","settings":{"text":"Powerful WordPress theme","text_color":"white","bg_color":"primary","delay":"0"},"elements":[],"isInner":false,"widgetType":"pix-badge","elType":"widget"},{"id":"5a4b61ea","settings":{"content":"The best performance and features on the market.","position":"left","size":"h3","_margin":{"unit":"px","top":"0","right":"0","bottom":"-20","left":"0","isLinked":false}},"elements":[],"isInner":false,"widgetType":"pix-sliding-text","elType":"widget"},{"id":"53523dce","settings":{"content":"This is just a simple text made for this unique and awesome template, you can replace it with any text.","size":"text-20","bold":"","content_color":"body-default","animation":"fade-in-up","delay":"900"},"elements":[],"isInner":false,"widgetType":"pix-text","elType":"widget"},{"id":"4af3bf60","settings":{"structure":"20"},"elements":[{"id":"165a105","settings":{"_column_size":50,"_inline_size":null},"elements":[{"id":"59570646","settings":{"percent":"85","title":"Finished Projects","text":"Since July 2020","color1":"#FFC845","color2":"#F48924","color3":"#F85A40","content_align":"left","animation":"fade-in-up","delay":"0","p_size":"h6"},"elements":[],"isInner":false,"widgetType":"pix-chart","elType":"widget"}],"isInner":true,"elType":"column"},{"id":"771cc11f","settings":{"_column_size":50,"_inline_size":null},"elements":[{"id":"392b6e1","settings":{"percent":"85","title":"Finished Projects","text":"Since July 2020","color1":"#FFC845","color2":"#F48924","color3":"#F85A40","content_align":"left","animation":"fade-in-up","delay":"0","p_size":"h6"},"elements":[],"isInner":false,"widgetType":"pix-chart","elType":"widget"}],"isInner":true,"elType":"column"}],"isInner":true,"elType":"section"},{"id":"3c150d9a","settings":{"btn_text":"Learn more about pricing","btn_link":"#pix_section_pricing","btn_color":"secondary","btn_effect":"2","btn_hover_effect":"2","btn_icon":"pixicon-angle-right","btn_icon_position":"after","btn_icon_animation":"yes","btn_animation":"fade-in-up","btn_anim_delay":"800"},"elements":[],"isInner":false,"widgetType":"pix-button","elType":"widget"}],"isInner":false,"elType":"column"},{"id":"54e3e73c","settings":{"_column_size":50,"_inline_size":null},"elements":[{"id":"2e7347ec","settings":{"image":{"url":"https:\/\/essentials.pixfort.com\/construction\/wp-content\/uploads\/sites\/20\/2020\/06\/p-6.jpg","id":3482},"title":"Create Beautiful Websites in no Time","badge":"Huge Discount","link_text":"Purchase Essentials WordPress Theme","link":"https:\/\/pixfort.website\/redirect?to=essentials","target":"Yes","xaxis":"0","yaxis":"0","delay":"0","height":"650px","secondary_font":"secondary-font","title_size":"h2","badge_text_color":"white","badge_bg_color":"secondary","badge_text_custom_size":"14px"},"elements":[],"isInner":false,"widgetType":"pix-promo-box","elType":"widget"}],"isInner":false,"elType":"column"}],"isInner":false,"elType":"section"}]}
