{"version":"0.4","title":"blogger","type":"page","content":[{"id":"27b00758","settings":{"stretch_section":"section-stretched","background_background":"slideshow","background_slideshow_gallery":[{"id":1289,"url":"https:\/\/essentials.pixfort.com\/blogger\/wp-content\/uploads\/sites\/31\/2020\/06\/intro-pattern-1.png"}],"background_slideshow_background_size":"cover","padding":{"unit":"px","top":"80","right":"0","bottom":"80","left":"0","isLinked":false}},"elements":[{"id":"5f86d850","settings":{"_column_size":100,"_inline_size":null,"align":"center"},"elements":[{"id":"6a3f9f9","settings":{"text":"Unlimited Possibilities","text_color":"heading-default","bg_color":"white","text_size":"custom","text_custom_size":"14px","style":"3","element_div":"text-center","animation":"fade-in-left","delay":"200"},"elements":[],"isInner":false,"widgetType":"pix-badge","elType":"widget"},{"id":"3cfa22e7","settings":{"content":"Marking things up with Essentials WordPress theme is a great way to get stuff done.","max_width":"850px","secondary_font":"secondary-font"},"elements":[],"isInner":false,"widgetType":"pix-sliding-text","elType":"widget"},{"id":"5fd91c03","settings":{"content":"Be ready to use the next generation of WordPress themes. Be ready to met Essentials by pixfort.","size":"text-20","bold":"","content_color":"body-default","position":"text-center","max_width":"560px","animation":"fade-in-up","delay":"1600","remove_pb_padding":"m-0"},"elements":[],"isInner":false,"widgetType":"pix-text","elType":"widget"},{"id":"51cae554","settings":{"btn_text":"Purchase Essentials","btn_link":"https:\/\/pixfort.website\/redirect?to=essentials","btn_target":"true","btn_style":"flat","btn_effect":"3","btn_hover_effect":"3","btn_icon":"pixicon-angle-right","btn_icon_position":"after","btn_icon_animation":"yes","btn_animation":"fade-in-up","btn_anim_delay":"1800","_margin":{"unit":"px","top":"0","right":"10","bottom":"10","left":"0","isLinked":false},"_element_width":"auto"},"elements":[],"isInner":false,"widgetType":"pix-button","elType":"widget"},{"id":"1efb5d13","settings":{"btn_text":"View our blog","btn_link":"https:\/\/pixfort.website\/redirect?to=essentials","btn_target":"true","btn_style":"underline","btn_color":"secondary","btn_text_color":"heading-default","btn_icon":"pixicon-slides-1","btn_icon_position":"after","btn_icon_animation":"yes","btn_animation":"fade-in-up","btn_anim_delay":"1800","_margin":{"unit":"px","top":"0","right":"0","bottom":"10","left":"0","isLinked":false},"_element_width":"auto"},"elements":[],"isInner":false,"widgetType":"pix-button","elType":"widget"}],"isInner":false,"elType":"column"}],"isInner":false,"elType":"section"},{"id":"10018451","settings":{"stretch_section":"section-stretched","background_background":"classic","background_color":"#FFFFFF","border_border":"solid","border_width":{"unit":"px","top":"1","right":"0","bottom":"1","left":"0","isLinked":false},"border_color":"rgba(0, 0, 0, 0.1)","padding":{"unit":"px","top":"40","right":"0","bottom":"40","left":"0","isLinked":false}},"elements":[{"id":"2981ef50","settings":{"_column_size":100,"_inline_size":null},"elements":[{"id":"2be95df0","settings":{"content":"Handpicked Articles","max_width":"850px","secondary_font":"secondary-font","size":"h5","_margin":{"unit":"px","top":"0","right":"0","bottom":"-20","left":"0","isLinked":false}},"elements":[],"isInner":false,"widgetType":"pix-sliding-text","elType":"widget"},{"id":"63081217","settings":{"content":"Selection of our best topics in the blog.","bold":"","content_color":"body-default","position":"text-center","max_width":"560px","animation":"fade-in-up","delay":"1600","remove_pb_padding":"m-0","_margin":{"unit":"px","top":"0","right":"0","bottom":"0","left":"0","isLinked":false}},"elements":[],"isInner":false,"widgetType":"pix-text","elType":"widget"},{"id":"3d82702b","settings":{"count":"7","orderby":"rand","order":"ASC","blog_style":"full-img","rounded_img":"rounded-lg","style":"1","hover_effect":"2","add_hover_effect":"1","xaxis":"0","yaxis":"0","slider_effect":"pix-circular-slider","cellpadding":"pix-p-20","autoplay_time":"1500","visible_y":"pix-overflow-y-visible","visible_overflow":"pix-overflow-all-visible"},"elements":[],"isInner":false,"widgetType":"pix-blog-slider","elType":"widget"}],"isInner":false,"elType":"column"}],"isInner":false,"elType":"section"},{"id":"567d8210","settings":{"stretch_section":"section-stretched","structure":"20","padding":{"unit":"px","top":"20","right":"0","bottom":"20","left":"0","isLinked":false},"border_border":"solid","border_width":{"unit":"px","top":"0","right":"0","bottom":"1","left":"0","isLinked":false},"border_color":"rgba(0, 0, 0, 0.08)","border_radius":{"unit":"px","top":"0","right":"0","bottom":"0","left":"0","isLinked":false}},"elements":[{"id":"19624c05","settings":{"_column_size":50,"_inline_size":69.386},"elements":[{"id":"6bc12d4a","settings":{"content":"Recent Articles","position":"left","max_width":"850px","secondary_font":"secondary-font","size":"h5","_margin":{"unit":"px","top":"0","right":"0","bottom":"-20","left":"0","isLinked":false}},"elements":[],"isInner":false,"widgetType":"pix-sliding-text","elType":"widget"},{"id":"3c66f9c6","settings":{"count":"6","items_count":"1","pagination":"true","rounded_img":"rounded-lg","style":"1","hover_effect":"2","add_hover_effect":"1","blog_style":"left-img","blog_style_box":"true"},"elements":[],"isInner":false,"widgetType":"pix-blog","elType":"widget"}],"isInner":false,"elType":"column"},{"id":"53c8fbcf","settings":{"_column_size":50,"_inline_size":30.57},"elements":[{"id":"7aaddd07","settings":{"sidebar":"sidebar-1","_css_classes":"sticky-top pix-sticky-top-adjust"},"elements":[],"isInner":false,"widgetType":"sidebar","elType":"widget"}],"isInner":false,"elType":"column"}],"isInner":false,"elType":"section"}]}