{"version":"0.4","title":"beauty-video-carousel","type":"section","content":[{"id":"2661b590","settings":{"stretch_section":"section-stretched","margin":{"unit":"px","top":"0","right":0,"bottom":"40","left":0,"isLinked":false},"padding":{"unit":"px","top":"60","right":"0","bottom":"0","left":"0","isLinked":false}},"elements":[{"id":"2f7f1294","settings":{"_column_size":100,"_inline_size":null},"elements":[{"id":"4abd54ea","settings":{"content":"Make Stunning Websites in Minutes!","size":"text-20","content_color":"heading-default","position":"text-center","max_width":"500px","animation":"fade-in-up","delay":"1000","remove_pb_padding":"m-0"},"elements":[],"isInner":false,"widgetType":"pix-text","elType":"widget"},{"id":"7412ec72","settings":{"content":"Some Beauty Tutorials","max_width":"650px","secondary_font":"secondary-font","size":"h2","text_color":"gradient-primary","_margin":{"unit":"px","top":"0","right":"0","bottom":"-20","left":"0","isLinked":false}},"elements":[],"isInner":false,"widgetType":"pix-sliding-text","elType":"widget"},{"id":"1a7e84a8","settings":{"content":"This is just a simple text made for Essentials awesome template.","size":"text-20","bold":"","content_color":"body-default","position":"text-center","max_width":"650px","animation":"fade-in-up","delay":"1000","remove_pb_padding":"m-0"},"elements":[],"isInner":false,"widgetType":"pix-text","elType":"widget"},{"id":"68f8d00","settings":{"btn_text":"Check our YouTube channel","btn_link":"https:\/\/essentials.pixfort.com\/beauty\/shop","btn_secondary_font":"secondary-font","btn_color":"white","btn_text_color":"heading-default","btn_effect":"1","btn_hover_effect":"2","btn_icon":"pixicon-play-circle","btn_icon_position":"after","btn_icon_animation":"yes","btn_animation":"fade-in-up","btn_anim_delay":"600","btn_div":"text-center"},"elements":[],"isInner":false,"widgetType":"pix-button","elType":"widget"}],"isInner":false,"elType":"column"}],"isInner":false,"elType":"section"},{"id":"56785afe","settings":{"structure":"30","z_index":1},"elements":[{"id":"7b6d884a","settings":{"_column_size":33,"_inline_size":null},"elements":[{"id":"119d33dc","settings":{"embed_code":"<iframe width=\"560\" height=\"315\" src=\"https:\/\/www.youtube.com\/embed\/uM4InNEGHkM\" frameborder=\"0\" allow=\"accelerometer; autoplay; encrypted-media; gyroscope; picture-in-picture\" allowfullscreen autoplay=\"autoplay\"><\/iframe>","image":{"url":"https:\/\/essentials.pixfort.com\/beauty\/wp-content\/uploads\/sites\/30\/2020\/06\/shipe-image-12.jpg","id":2673},"aspect":"embed-responsive-4by3","rounded_img":"rounded-xl","xaxis":"0","yaxis":"0","animation":"fade-in-up","delay":"0","text_color":"heading-default","size":"100","overlay_color":"gradient-primary","overlay_opacity":"pix-opacity-7","style":"3","hover_effect":"3","add_hover_effect":"1","_margin":{"unit":"px","top":"10","right":"0","bottom":"10","left":"0","isLinked":false}},"elements":[],"isInner":false,"widgetType":"pix-video","elType":"widget"}],"isInner":false,"elType":"column"},{"id":"45bdbab2","settings":{"_column_size":33,"_inline_size":null},"elements":[{"id":"7869ee7d","settings":{"embed_code":"<iframe width=\"560\" height=\"315\" src=\"https:\/\/www.youtube.com\/embed\/uM4InNEGHkM\" frameborder=\"0\" allow=\"accelerometer; autoplay; encrypted-media; gyroscope; picture-in-picture\" allowfullscreen autoplay=\"autoplay\"><\/iframe>","image":{"url":"https:\/\/essentials.pixfort.com\/beauty\/wp-content\/uploads\/sites\/30\/2020\/06\/shipe-image-9.jpg","id":2670},"aspect":"embed-responsive-4by3","rounded_img":"rounded-xl","xaxis":"0","yaxis":"0","animation":"fade-in-up","delay":"0","text_color":"heading-default","size":"100","overlay_color":"gradient-primary","overlay_opacity":"pix-opacity-7","style":"3","hover_effect":"3","add_hover_effect":"1","_margin":{"unit":"px","top":"10","right":"0","bottom":"10","left":"0","isLinked":false}},"elements":[],"isInner":false,"widgetType":"pix-video","elType":"widget"}],"isInner":false,"elType":"column"},{"id":"50c55c86","settings":{"_column_size":33,"_inline_size":null},"elements":[{"id":"e21c9a7","settings":{"embed_code":"<iframe width=\"560\" height=\"315\" src=\"https:\/\/www.youtube.com\/embed\/uM4InNEGHkM\" frameborder=\"0\" allow=\"accelerometer; autoplay; encrypted-media; gyroscope; picture-in-picture\" allowfullscreen autoplay=\"autoplay\"><\/iframe>","image":{"url":"https:\/\/essentials.pixfort.com\/beauty\/wp-content\/uploads\/sites\/30\/2020\/06\/shipe-image-10.jpg","id":2671},"aspect":"embed-responsive-4by3","rounded_img":"rounded-xl","xaxis":"0","yaxis":"0","animation":"fade-in-up","delay":"0","text_color":"heading-default","size":"100","overlay_color":"gradient-primary","overlay_opacity":"pix-opacity-7","style":"3","hover_effect":"3","add_hover_effect":"1","_margin":{"unit":"px","top":"10","right":"0","bottom":"10","left":"0","isLinked":false}},"elements":[],"isInner":false,"widgetType":"pix-video","elType":"widget"}],"isInner":false,"elType":"column"}],"isInner":false,"elType":"section"},{"id":"4b0305c9","settings":{"stretch_section":"section-stretched","layout":"full_width","gap":"no"},"elements":[{"id":"7e36bd09","settings":{"_column_size":100,"_inline_size":null},"elements":[{"id":"691f869c","settings":{"bottom_divider_select":"8","bottom_moving_divider_color":[{"d_gradient":"","_id":"a856a29","d_color_1":"#f8f9fa","d_color_2":"#f8f9fa"},{"_id":"41bcca5","d_gradient":"","d_color_1":"#f8f9fa","d_color_2":"#f8f9fa"}],"b_custom_height":"0","b_1_color":"#F8F9FA","b_1_delay":"0","b_2_is_gradient":"true","b_2_color":"rgba(233, 236, 239, 0.5)","b_2_delay":"0","b_3_is_gradient":"true","b_3_color":"rgba(255, 255, 255, 0.01)","b_3_color_2":"rgba(206, 196, 177, 0.5)","b_3_delay":"0","top_moving_divider_color":[{"d_gradient":"","_id":"98c232e","d_color_1":"#f8f9fa","d_color_2":"#f8f9fa"},{"_id":"5bf66d0","d_gradient":"","d_color_1":"#f8f9fa","d_color_2":"#f8f9fa"}],"t_custom_height":"0","t_1_delay":"0","t_2_delay":"0","t_3_delay":"0","_margin":{"unit":"px","top":"-375","right":"0","bottom":"0","left":"0","isLinked":false},"_z_index":0},"elements":[],"isInner":false,"widgetType":"pix-dividers","elType":"widget"}],"isInner":false,"elType":"column"}],"isInner":false,"elType":"section"}]}
